LICENCE
README.md
setup.py
SimpleCall931.egg-info/PKG-INFO
SimpleCall931.egg-info/SOURCES.txt
SimpleCall931.egg-info/dependency_links.txt
SimpleCall931.egg-info/requires.txt
SimpleCall931.egg-info/top_level.txt
simple/__init__.py
simple/cal_preco.py