Metadata-Version: 2.1
Name: SimpleCall931
Version: 0.0.1
Summary: Pacote não oficial
Home-page: UNKNOWN
Author: José Pádua
Author-email: josegabrielpadua@gmail.com
License: MIT License
Keywords: simple calculator
Platform: UNKNOWN
License-File: LICENCE
